{"id":"ac86ba22-e67a-4f59-95da-cb267e60ffa1","firstname":"Paige","lastname":"Holt","fullname":"Paige Holt","gender":"Female","image":"https:\/\/picsum.photos\/id\/281\/200\/300.jpg","status":"C1","birth_date":"1992-01-14","nationality":"Bosnia and Herzegovina","phone_numbers":[{"phone":"+1-936-411-1425"},{"phone":"001-689-735-2518x7167"},{"phone":"+1-779-875-1166"}],"main_phone":"+1-779-875-1166","credit_cards":[{"card":"180016119455424"},{"card":"4758514954248411"}],"main_card":180016119455424,"address":{"country":"Peru","city":"Thomasbury","district":"Jessica Points","neighborhood":"Johnson Inlet","street":"67313 Byrd Forest","house":"86","apartment":"Suite 162","house_phone":"4446154609"},"salary":[{"date":"2024-09-16","all_sum":8100,"inps":81,"to_hand":8019,"workplace":"Contreras, Keith and Petersen"},{"date":"2024-10-16","all_sum":6600,"inps":66,"to_hand":6534,"workplace":"Franklin-Kelly"}],"hobbies":["Learning","Playing sports","Designing","Playing basketball","Model building"],"workplace":[{"start_date":"2021-10-12","end_date":"2023-09-15","name":"Stephens, Baker and Gibson","address":"1311 Jeffery Drive\nOlsonshire, NC 41883","call_center":"(427)922-2490x3473"}],"studied":[{"start_date":"2016-02-12","end_date":"2091-02-14","name":"Sutton-Downs","address":"Unit 3034 Box 4028\nDPO AP 19325"},{"start_date":"2008-02-05","end_date":"2062-02-13","name":"Carter and Sons","address":"211 Amanda Stream Suite 806\nSouth Isaiah, TN 58221"}],"user_status":false}
