{"id":"7a8ef917-b7eb-4f6a-a850-d6853665b33b","firstname":"Stephanie","lastname":"Cooper","fullname":"Stephanie Cooper","gender":"Female","image":"https:\/\/picsum.photos\/id\/210\/200\/300.jpg","status":"B2","birth_date":"2000-08-23","nationality":"Niger","phone_numbers":[{"phone":"(628)815-7546"},{"phone":"+1-800-873-8740x5423"}],"main_phone":"+1-800-873-8740x5423","credit_cards":[{"card":"4294489438262"},{"card":"3596573633382601"}],"main_card":4294489438262,"address":{"country":"Seychelles","city":"Frankmouth","district":"Gary Mills","neighborhood":"Clements Keys","street":"53669 Jerry Ramp Apt. 877","house":"8","apartment":"Suite 116","house_phone":"6972809241"},"salary":[{"date":"2024-12-02","all_sum":9000,"inps":90,"to_hand":8910,"workplace":"Anderson Ltd"},{"date":"2024-01-02","all_sum":9300,"inps":93,"to_hand":9207,"workplace":"Perry, Nolan and Hill"},{"date":"2024-02-02","all_sum":5900,"inps":59,"to_hand":5841,"workplace":"Scott and Sons"},{"date":"2024-03-02","all_sum":8700,"inps":87,"to_hand":8613,"workplace":"Smith Ltd"},{"date":"2024-04-02","all_sum":6500,"inps":65,"to_hand":6435,"workplace":"Perkins-Jordan"},{"date":"2024-05-02","all_sum":8000,"inps":80,"to_hand":7920,"workplace":"Collins-Jackson"},{"date":"2024-06-02","all_sum":9100,"inps":91,"to_hand":9009,"workplace":"Harrison Ltd"},{"date":"2024-07-02","all_sum":9300,"inps":93,"to_hand":9207,"workplace":"Hoffman, Peck and Tyler"}],"hobbies":["Learning","Listening to music","Culinary arts","Watching movies and TV shows"],"workplace":[{"start_date":"2022-08-30","end_date":"2022-07-07","name":"Castro-Fernandez","address":"7772 Oliver Roads Apt. 644\nKarenfort, ID 75137","call_center":"919-601-4747x29126"},{"start_date":"2023-07-06","end_date":"2022-12-05","name":"Fuentes, Thompson and Rhodes","address":"97520 Thompson Viaduct\nSouth Danielle, AL 16670","call_center":"+1-798-936-3866"}],"studied":[{"start_date":"2009-06-16","end_date":"2020-06-08","name":"Lewis-Sanchez","address":"20967 Mayer Land Apt. 294\nLoganmouth, VI 79150"}],"user_status":false}
