{"id":"f7436420-b0af-42f3-8071-074316ea2950","firstname":"Jeffrey","lastname":"Baker","fullname":"Jeffrey Baker","gender":"Male","image":"https:\/\/picsum.photos\/id\/254\/200\/300.jpg","status":"A2","birth_date":"1996-08-09","nationality":"Greece","phone_numbers":[{"phone":"001-282-438-6857x7053"},{"phone":"001-803-382-0582x21062"},{"phone":"205-640-0158x6841"}],"main_phone":"205-640-0158x6841","credit_cards":[{"card":"675976629583"},{"card":"180049678367342"}],"main_card":675976629583,"address":{"country":"Iraq","city":"Cookfurt","district":"Anne Landing","neighborhood":"Lamb Pike","street":"93230 Martinez Lakes","house":"15","apartment":"Suite 943","house_phone":"3265484850"},"salary":[{"date":"2024-07-08","all_sum":5500,"inps":55,"to_hand":5445,"workplace":"Washington, Arnold and Warner"},{"date":"2024-08-08","all_sum":8600,"inps":86,"to_hand":8514,"workplace":"Johnson and Sons"},{"date":"2024-09-08","all_sum":7500,"inps":75,"to_hand":7425,"workplace":"Acosta Group"},{"date":"2024-10-08","all_sum":5700,"inps":57,"to_hand":5643,"workplace":"Rosales, Simmons and Herrera"},{"date":"2024-11-08","all_sum":8800,"inps":88,"to_hand":8712,"workplace":"Jones, Harper and Green"},{"date":"2024-12-08","all_sum":5400,"inps":54,"to_hand":5346,"workplace":"Green Ltd"},{"date":"2024-01-08","all_sum":10000,"inps":100,"to_hand":9900,"workplace":"Morris Group"},{"date":"2024-02-08","all_sum":5800,"inps":58,"to_hand":5742,"workplace":"Ramirez LLC"},{"date":"2024-03-08","all_sum":8200,"inps":82,"to_hand":8118,"workplace":"Jacobson LLC"},{"date":"2024-04-08","all_sum":7600,"inps":76,"to_hand":7524,"workplace":"Martinez and Sons"}],"hobbies":["Drawing"],"workplace":[{"start_date":"2021-02-19","end_date":"2023-02-19","name":"Hodges, Zamora and Kent","address":"315 Pena Hills\nSteinfort, WY 75452","call_center":"001-262-202-3875x344"},{"start_date":"2020-04-10","end_date":"2022-03-08","name":"Anderson, Lawrence and Reid","address":"95141 Hall Key\nNorth Kirk, LA 13160","call_center":"001-330-519-5253x8422"}],"studied":[{"start_date":"2022-02-23","end_date":"2053-08-17","name":"Love, Allen and Bautista","address":"Unit 6161 Box 7435\nDPO AP 90674"}],"user_status":false}
