{"id":"561c3fd9-4f3e-465e-81aa-5e5303c647d9","firstname":"Mark","lastname":"Lewis","fullname":"Mark Lewis","gender":"Male","image":"https:\/\/picsum.photos\/id\/227\/200\/300.jpg","status":"C1","birth_date":"1999-01-02","nationality":"Netherlands","phone_numbers":[{"phone":"6914742320"},{"phone":"944.950.7931x199"}],"main_phone":"944.950.7931x199","credit_cards":[{"card":"2261160442704310"},{"card":"2505794671685547"}],"main_card":2261160442704310,"address":{"country":"Afghanistan","city":"New Richardside","district":"Flores Extensions","neighborhood":"White Light","street":"814 Greer Rest","house":"41","apartment":"Apt. 261","house_phone":"652.405.1232x42228"},"salary":[{"date":"2024-12-30","all_sum":9100,"inps":91,"to_hand":9009,"workplace":"Baker Ltd"},{"date":"2024-01-30","all_sum":9700,"inps":97,"to_hand":9603,"workplace":"Livingston LLC"},{"date":"2024-02-30","all_sum":7500,"inps":75,"to_hand":7425,"workplace":"Stark, Horton and Harris"}],"hobbies":["Cooking","Running","Sewing","Reading"],"workplace":[{"start_date":"2023-04-16","end_date":"2022-07-24","name":"Moore Group","address":"Unit 7926 Box 0318\nDPO AE 89189","call_center":"(238)706-8308x16163"},{"start_date":"2021-08-15","end_date":"2021-06-11","name":"Turner Inc","address":"346 Moore Island Apt. 194\nGreenton, CA 01243","call_center":"379-249-4714x27070"},{"start_date":"2024-03-19","end_date":"2021-01-03","name":"Schaefer-Miles","address":"448 Melissa Common\nWest Thomasfort, OR 84894","call_center":"616.573.8031x4371"}],"studied":[{"start_date":"2022-08-29","end_date":"2018-02-09","name":"Rodriguez-Strickland","address":"Unit 3247 Box 1109\nDPO AA 27885"}],"user_status":false}
