{"id":"c6143ee3-7cd2-4d8e-b315-cfd83a629fba","firstname":"Paul","lastname":"Wallace","fullname":"Paul Wallace","gender":"Male","image":"https:\/\/picsum.photos\/id\/282\/200\/300.jpg","status":"A2","birth_date":"1990-01-27","nationality":"Singapore","phone_numbers":[{"phone":"4939674168"},{"phone":"(625)918-3796x513"},{"phone":"(372)211-9249"}],"main_phone":"(372)211-9249","credit_cards":[{"card":"501827097608"},{"card":"3594329546416289"}],"main_card":501827097608,"address":{"country":"Afghanistan","city":"Cookmouth","district":"Miller Route","neighborhood":"White Islands","street":"021 Kimberly Vista Suite 872","house":"10","apartment":"Suite 181","house_phone":"001-484-550-2181x864"},"salary":[{"date":"2024-09-18","all_sum":7200,"inps":72,"to_hand":7128,"workplace":"Nichols-Lopez"},{"date":"2024-10-18","all_sum":6900,"inps":69,"to_hand":6831,"workplace":"Bradshaw, Hardin and Diaz"},{"date":"2024-11-18","all_sum":6000,"inps":60,"to_hand":5940,"workplace":"Robinson, Wilson and Gallegos"},{"date":"2024-12-18","all_sum":7300,"inps":73,"to_hand":7227,"workplace":"Powell Inc"},{"date":"2024-01-18","all_sum":7100,"inps":71,"to_hand":7029,"workplace":"Gomez LLC"},{"date":"2024-02-18","all_sum":6000,"inps":60,"to_hand":5940,"workplace":"Mason-Taylor"},{"date":"2024-03-18","all_sum":7600,"inps":76,"to_hand":7524,"workplace":"Navarro-Rivas"},{"date":"2024-04-18","all_sum":5700,"inps":57,"to_hand":5643,"workplace":"Smith Ltd"},{"date":"2024-05-18","all_sum":9300,"inps":93,"to_hand":9207,"workplace":"Williams PLC"},{"date":"2024-06-18","all_sum":8500,"inps":85,"to_hand":8415,"workplace":"Jennings LLC"},{"date":"2024-07-18","all_sum":8800,"inps":88,"to_hand":8712,"workplace":"Johnson-Tran"}],"hobbies":["Writing"],"workplace":[{"start_date":"2023-04-05","end_date":"2020-03-11","name":"Giles, Reed and Cook","address":"1860 Flores River Suite 219\nEmilyview, CO 12135","call_center":"2696580102"}],"studied":[{"start_date":"2021-02-21","end_date":"2028-01-17","name":"Horne LLC","address":"3417 Montgomery Way Apt. 151\nPort Kaitlynburgh, NM 35494"}],"user_status":false}
