{"id":"96fe3970-71a7-4bae-8cf4-4d56ed43c5bc","firstname":"Debra","lastname":"Wilkinson","fullname":"Debra Wilkinson","gender":"Female","image":"https:\/\/picsum.photos\/id\/230\/200\/300.jpg","status":"C1","birth_date":"1991-10-10","nationality":"Central African Republic","phone_numbers":[{"phone":"001-531-493-3135x63775"},{"phone":"247.868.3990"}],"main_phone":"247.868.3990","credit_cards":[{"card":"30128439542427"},{"card":"342952155693343"}],"main_card":30128439542427,"address":{"country":"Burundi","city":"New Derek","district":"Stephen Meadows","neighborhood":"Lee Stream","street":"51897 Evans Green","house":"38","apartment":"Apt. 242","house_phone":"897-454-6993x088"},"salary":[{"date":"2024-10-26","all_sum":5700,"inps":57,"to_hand":5643,"workplace":"Horn Inc"},{"date":"2024-11-26","all_sum":6100,"inps":61,"to_hand":6039,"workplace":"Schmitt-Olson"},{"date":"2024-12-26","all_sum":7700,"inps":77,"to_hand":7623,"workplace":"Williams-Jones"},{"date":"2024-01-26","all_sum":7300,"inps":73,"to_hand":7227,"workplace":"Middleton-Carter"},{"date":"2024-02-26","all_sum":7500,"inps":75,"to_hand":7425,"workplace":"Morales, Page and Hall"},{"date":"2024-03-26","all_sum":7100,"inps":71,"to_hand":7029,"workplace":"Richardson Group"},{"date":"2024-04-26","all_sum":9300,"inps":93,"to_hand":9207,"workplace":"Holmes-Todd"},{"date":"2024-05-26","all_sum":9200,"inps":92,"to_hand":9108,"workplace":"Osborne, Strickland and Ross"},{"date":"2024-06-26","all_sum":8800,"inps":88,"to_hand":8712,"workplace":"Henderson Ltd"},{"date":"2024-07-26","all_sum":7800,"inps":78,"to_hand":7722,"workplace":"Johnson, Butler and Nguyen"},{"date":"2024-08-26","all_sum":9800,"inps":98,"to_hand":9702,"workplace":"Sutton LLC"}],"hobbies":["Sewing","Origami","Hiking","Playing golf"],"workplace":[{"start_date":"2021-03-16","end_date":"2020-10-01","name":"Bailey LLC","address":"42382 Roy Underpass Suite 501\nNorth Becky, TN 97082","call_center":"+1-389-261-6447x550"},{"start_date":"2023-06-04","end_date":"2021-03-22","name":"Davis-Allen","address":"14770 Melissa View Apt. 792\nSouth Julie, OH 17425","call_center":"543-666-9992"},{"start_date":"2020-09-22","end_date":"2020-03-04","name":"Cannon, Martinez and Barnes","address":"03622 Wesley Circles\nPort Pamela, MP 53389","call_center":"+1-800-682-2859x667"}],"studied":[{"start_date":"2001-04-06","end_date":"2081-10-14","name":"Hill, Wang and Keith","address":"836 Bradley Valley Suite 569\nKimberlyville, WY 15990"},{"start_date":"2016-08-07","end_date":"2056-04-29","name":"Adams Group","address":"27305 Davidson Square\nTapiatown, OH 49564"}],"user_status":false}
