{"id":"c7c7f9ba-55b5-4d95-bafc-7696186882ab","firstname":"Donald","lastname":"Griffith","fullname":"Donald Griffith","gender":"Male","image":"https:\/\/picsum.photos\/id\/217\/200\/300.jpg","status":"A2","birth_date":"1990-09-01","nationality":"Peru","phone_numbers":[{"phone":"+1-457-651-3467x1729"},{"phone":"907-994-2642x178"}],"main_phone":"907-994-2642x178","credit_cards":[{"card":"372294337709983"},{"card":"4741215454591660"}],"main_card":372294337709983,"address":{"country":"Korea","city":"Duncanport","district":"Daniel Key","neighborhood":"John Fall","street":"2152 Espinoza Dam Apt. 094","house":"31","apartment":"Apt. 762","house_phone":"001-986-498-3552"},"salary":[{"date":"2024-10-12","all_sum":7300,"inps":73,"to_hand":7227,"workplace":"Harrison, Wiley and Carroll"},{"date":"2024-11-12","all_sum":7500,"inps":75,"to_hand":7425,"workplace":"Gray-Daniel"},{"date":"2024-12-12","all_sum":6200,"inps":62,"to_hand":6138,"workplace":"Turner-Barker"},{"date":"2024-01-12","all_sum":9100,"inps":91,"to_hand":9009,"workplace":"Anderson-Smith"}],"hobbies":["Model building","Traveling"],"workplace":[{"start_date":"2024-04-05","end_date":"2020-09-24","name":"Friedman, Carroll and Esparza","address":"2569 Barrett Grove Apt. 244\nNorth Julieshire, MI 75112","call_center":"(907)803-4662x4561"}],"studied":[{"start_date":"2022-05-06","end_date":"2013-10-27","name":"Reyes Inc","address":"021 Michelle Junctions\nRamoshaven, GU 88987"}],"user_status":false}
