{"id":"e4374364-d62a-496d-bb18-e820b8389184","firstname":"Kyle","lastname":"Johnson","fullname":"Kyle Johnson","gender":"Male","image":"https:\/\/picsum.photos\/id\/207\/200\/300.jpg","status":"A1","birth_date":"1997-02-13","nationality":"South Georgia and the South Sandwich Islands","phone_numbers":[{"phone":"+1-487-818-7425x53022"},{"phone":"+1-565-851-6962x184"},{"phone":"216.501.0176x0849"}],"main_phone":"216.501.0176x0849","credit_cards":[{"card":"213131788848402"},{"card":"374516059829104"}],"main_card":213131788848402,"address":{"country":"Peru","city":"South Anthony","district":"Jerry Centers","neighborhood":"Gentry Heights","street":"931 Gonzalez Light Apt. 103","house":"93","apartment":"Suite 211","house_phone":"9955325596"},"salary":[{"date":"2024-06-13","all_sum":6900,"inps":69,"to_hand":6831,"workplace":"Patel-Quinn"},{"date":"2024-07-13","all_sum":6800,"inps":68,"to_hand":6732,"workplace":"Erickson, Sawyer and Cooper"},{"date":"2024-08-13","all_sum":5700,"inps":57,"to_hand":5643,"workplace":"Robinson, Barnett and Morgan"},{"date":"2024-09-13","all_sum":5300,"inps":53,"to_hand":5247,"workplace":"Gomez-Coffey"},{"date":"2024-10-13","all_sum":8000,"inps":80,"to_hand":7920,"workplace":"Bray Group"},{"date":"2024-11-13","all_sum":5300,"inps":53,"to_hand":5247,"workplace":"Guerrero, Jacobs and Barrera"},{"date":"2024-12-13","all_sum":7600,"inps":76,"to_hand":7524,"workplace":"Snyder, Brooks and Patrick"},{"date":"2024-01-13","all_sum":6900,"inps":69,"to_hand":6831,"workplace":"Sanchez, Webster and Walker"},{"date":"2024-02-13","all_sum":5600,"inps":56,"to_hand":5544,"workplace":"Contreras-Vazquez"},{"date":"2024-03-13","all_sum":7400,"inps":74,"to_hand":7326,"workplace":"Rubio-Howard"},{"date":"2024-04-13","all_sum":6700,"inps":67,"to_hand":6633,"workplace":"Gray-Duncan"}],"hobbies":["Drawing","Reading"],"workplace":[{"start_date":"2022-01-18","end_date":"2024-06-28","name":"Ward, Peterson and Peters","address":"8910 Eaton Curve Suite 553\nPort Chadville, WV 54866","call_center":"(226)822-7749x8809"},{"start_date":"2020-01-16","end_date":"2021-02-17","name":"Obrien and Sons","address":"5558 Jones Mountains Suite 952\nCassandraland, MS 22121","call_center":"001-898-453-2948x24982"}],"studied":[{"start_date":"2016-10-13","end_date":"2049-06-06","name":"Green, Burton and Stein","address":"Unit 8300 Box 7537\nDPO AP 95723"}],"user_status":false}
