{"id":"5460b800-9e0f-403d-aeb9-245d89058e92","firstname":"Christina","lastname":"Evans","fullname":"Christina Evans","gender":"Female","image":"https:\/\/picsum.photos\/id\/289\/200\/300.jpg","status":"B1","birth_date":"2002-04-02","nationality":"United Arab Emirates","phone_numbers":[{"phone":"5358914282"}],"main_phone":"5358914282","credit_cards":[{"card":"3511538418876301"},{"card":"344098624148762"}],"main_card":3511538418876301,"address":{"country":"Zambia","city":"South Meganshire","district":"Johnson Road","neighborhood":"Torres Villages","street":"156 Serrano Way Apt. 713","house":"10","apartment":"Apt. 444","house_phone":"754.979.7130"},"salary":[{"date":"2024-06-04","all_sum":5500,"inps":55,"to_hand":5445,"workplace":"Lyons Group"}],"hobbies":["Culinary arts","Watching movies and TV shows","Watching movies and TV shows"],"workplace":[{"start_date":"2024-07-13","end_date":"2021-04-26","name":"Austin-Snyder","address":"9211 Jacqueline Plaza Apt. 473\nDavidside, GA 94021","call_center":"(205)555-9382"}],"studied":[{"start_date":"2019-02-23","end_date":"2081-02-21","name":"Mclaughlin-Rice","address":"09485 Long Brook Suite 211\nRobinsonberg, KS 45963"}],"user_status":false}
